{
  "AGUAS-A": "Aguas Andinas",
  "CHILE": "Banco de Chile",
  "BCI": "Banco de Crédito e Inversiones",
  "ITAUCL": "Banco Itaú Chile",
  "BSANTANDER": "Banco Santander Chile",
  "CAP": "CAP",
  "CENCOSUD": "Cencosud",
  "CENCOMALLS": "Cencosud Shopping",
  "COLBUN": "Colbún",
  "CCU": "Compañía Cervecerías Unidas",
  "VAPORES": "Cía. Sud Americana de Vapores",
  "ANDINA-B": "Embotelladora Andina",
  "ENTEL": "Entel",
  "CMPC": "Empresas CMPC",
  "COPEC": "Empresas Copec",
  "ENELAM": "Enel Américas",
  "ENELCHILE": "Enel Chile",
  "ECL": "Engie Energía Chile",
  "FALABELLA": "Falabella",
  "IAM": "Inversiones Aguas Metropolitanas",
  "ILC": "Inversiones La Construcción",
  "LTM": "Latam Airlines Group",
  "PARAUCO": "Parque Arauco",
  "MALLPLAZA": "Plaza",
  "QUINENCO": "Quiñenco",
  "RIPLEY": "Ripley Corp",
  "SALFACORP": "Salfacorp",
  "SMU": "SMU",
  "SQM-B": "SQM",
  "CONCHATORO": "Viña Concha y Toro"
}
